elio/__init__.py
elio/comm/__init__.py
elio/comm/command.py
elio/comm/comtimer.py
elio/comm/eliochannel.py
elio/comm/elioprotocol.py
elio/comm/packet_t.py
elio/comm/protocol.py
elio/example/__init__.py
elio/example/hello_elio.py
elio-3.0.4.dist-info/METADATA
elio-3.0.4.dist-info/WHEEL
elio-3.0.4.dist-info/top_level.txt
elio-3.0.4.dist-info/RECORD
