Metadata-Version: 2.1
Name: elio
Version: 3.0.4
Summary: elio board python interface
Home-page: https://github.com/johnsnow-nam/elio
Author: elio robotics
Author-email: caram88@mobilian.biz
License: MIT
Platform: UNKNOWN
Classifier: Programming Language :: Python :: 2
Classifier: Programming Language :: Python :: 3
Classifier: License :: OSI Approved :: MIT License
Classifier: Operating System :: OS Independent
Requires-Python: >=2.7
Requires-Dist: pyserial
